tabassist/__init__.py
tabassist/__main__.py
tabassist/check.py
tabassist/doc.py
tabassist/error.py
tabassist/log.py
tabassist/data/template.md
tabassist-0.2.2.dist-info/LICENCE
tabassist-0.2.2.dist-info/METADATA
tabassist-0.2.2.dist-info/WHEEL
tabassist-0.2.2.dist-info/entry_points.txt
tabassist-0.2.2.dist-info/top_level.txt
tabassist-0.2.2.dist-info/RECORD
