Metadata-Version: 2.1
Name: tabassist
Version: 0.2.2
Summary: Command line utility to work with Tableau workbook faster.
Home-page: https://github.com/dev-mkc19/tabassist
Author: Mikhail Korotchenkov
Author-email: mr.mkc19@hotmail.com
Project-URL: Bug Tracker, https://github.com/dev-mkc19/tabassist/issues
Keywords: tableau cli-app
Platform: any
Classifier: Programming Language :: Python :: 3
Classifier: License :: OSI Approved :: MIT License
Classifier: Operating System :: OS Independent
Classifier: Intended Audience :: Developers
Requires-Python: >=3.7
License-File: LICENCE
Requires-Dist: click (==8.0.1)
Requires-Dist: tableaudocumentapi (==0.11)
Requires-Dist: Jinja2 (==3.0.2)
